SPC/CControlChart.py
SPC/ControlChart.py
SPC/ControlChartConstants.py
SPC/ImRControlChart.py
SPC/MultiVariChart.py
SPC/NPControlChart.py
SPC/PControlChart.py
SPC/ProcessCapabilityChart.py
SPC/Rule.py
SPC/Rule01.py
SPC/Rule02.py
SPC/Rule03.py
SPC/Rule04.py
SPC/Rule05.py
SPC/Rule06.py
SPC/Rule07.py
SPC/Rule08.py
SPC/UControlChart.py
SPC/XbarRControlChart.py
SPC/XbarRControlChartConstants.py
SPC/XbarSControlChart.py
SPC/XbarSControlChartConstants.py
SPC/XbarmRControlChart.py
SPC/XmRControlChart.py
SPC/__init__.py
tests/CControlChart.py
tests/ImRControlChart.py
tests/MultiVariChartTest.py
tests/NPControlChart.py
tests/PControlChart.py
tests/ProcessCapabilityChartTest.py
tests/UControlChart.py
tests/XbarRControlChartTest.py
tests/XbarSControlChart.py
tests/XbarmRControlChart.py
tests/XmRControlChart.py
tests/__init__.py
sixsigmaspc-1.0.7.dist-info/LICENSE
sixsigmaspc-1.0.7.dist-info/METADATA
sixsigmaspc-1.0.7.dist-info/WHEEL
sixsigmaspc-1.0.7.dist-info/top_level.txt
sixsigmaspc-1.0.7.dist-info/RECORD
