Metadata-Version: 2.1
Name: sixsigmaspc
Version: 1.0.7
Summary: Statistical Process Control library
Home-page: https://sixsigmaspc.readthedocs.io/
Author: Junior Marte Garcia, Marcel van Velzen
Author-email: 
License: MIT
Classifier: Intended Audience :: Developers
Classifier: License :: OSI Approved :: MIT License
Classifier: Programming Language :: Python
Classifier: Programming Language :: Python :: 3
Classifier: Programming Language :: Python :: 3.6
Classifier: Programming Language :: Python :: 3.7
Classifier: Programming Language :: Python :: 3.8
Classifier: Programming Language :: Python :: 3.9
Classifier: Operating System :: OS Independent
License-File: LICENSE
Requires-Dist: python-abc
Requires-Dist: datetime
Requires-Dist: kneed
Requires-Dist: matplotlib
Requires-Dist: numpy
Requires-Dist: pandas
Requires-Dist: ruptures
Requires-Dist: scipy
Requires-Dist: statistics
Requires-Dist: statsmodels
